EasyTTS/__init__.py
EasyTTS/version.txt
EasyTTS/inference/TTS.py
EasyTTS/inference/__init__.py
EasyTTS/models/__init__.py
EasyTTS/utils/__init__.py
EasyTTS-0.3.2.dist-info/LICENSE
EasyTTS-0.3.2.dist-info/METADATA
EasyTTS-0.3.2.dist-info/WHEEL
EasyTTS-0.3.2.dist-info/top_level.txt
EasyTTS-0.3.2.dist-info/RECORD
