Metadata-Version: 2.1
Name: EasyTTS
Version: 0.3.2
Summary: Ready-to-use Multilingual Text-To-Speech (TTS) package.
Home-page: https://EasyTTS.github.io/
Author: Yanis Labrak & Others
Author-email: yanis.labrak@univ-avignon.fr
License: UNKNOWN
Keywords: python,transformers,huggingface,wrapper,toolkit,speech,text-to-speech,text2speech,text-2-speech,T2S,easy,voice,vocal synthesis,synthesis,Speech synthesis
Platform: UNKNOWN
Requires-Python: >=3.7
Requires-Dist: numpy
Requires-Dist: timm
Requires-Dist: torch
Requires-Dist: tensorflow
Requires-Dist: soundfile
Requires-Dist: TensorFlowTTS
